Simple Binary elements/adder.v
module not_gate(in, out);
        input wire in;
        output wire out;

        supply1 vdd;
        supply0 gnd;

        wire nmos_out;
        nmos nmos1(out, gnd, in);
        pmos pmos1(out, vdd, in);
endmodule

module nand_gate(in1, in2, out);
	input wire in1, in2;
	output wire out;
	
	supply1 vdd;
	supply0 gnd;

	wire nmos_out;
	pmos pmos1(out,vdd,in1);
	pmos pmos2(out,vdd,in2);
	nmos nmos1(nmos_out,gnd,in2);
	nmos nmos2(out,nmos_out,in1);
endmodule

module nor_gate(in1, in2, out);
	input wire in1, in2;
        output wire out;

        supply1 vdd;
        supply0 gnd;

        wire pmos_out;
        pmos pmos1(pmos_out,vdd,in1);
        pmos pmos2(out,pmos_out,in2);
        nmos nmos1(out,gnd,in1);
        nmos nmos2(out,gnd,in2);
endmodule

module and_gate(in1, in2, out);
	input wire in1, in2;
        output wire out;

        supply1 vdd;
        supply0 gnd;

	wire mos;
	nand_gate nand1(in1,in2,mos);
	not_gate not1(mos,out);
endmodule

module or_gate(in1, in2, out);
	input wire in1, in2;
        output wire out;

        supply1 vdd;
        supply0 gnd;

        wire mos;
        nor_gate nand1(in1,in2,mos);
        not_gate not1(mos,out);
endmodule

module xor_gate(in1, in2, out);
	input wire in1, in2;
        output wire out;

        supply1 vdd;
        supply0 gnd;
	
	wire out_1;
	wire out_2;
	wire out_3;
	or_gate or1(in1,in2,out_1);
	and_gate and1(in1,in2,out_2);
	not_gate not1(out_2,out_3);
	and_gate and2(out_1,out_3,out);
endmodule

module half_adder(in1, in2, out, c);
	input wire in1, in2;
        output wire out, c;

        supply1 vdd;
        supply0 gnd;
	and_gate andgate(in1,in2,out);
	xor_gate xorgate(in1,in2,c);
endmodule

module adder(in1, in2, cin, cout, out);
	input wire in1, in2, cin;
        output wire cout, out;

        supply1 vdd;
        supply0 gnd;
	wire out_1;
	wire out_2;
	wire out_3;
	xor_gate xorgate1(in1,in2,out_1);
	and_gate andgate1(in1,in2,out_2);
	xor_gate xorgate2(out_1,cin,out);
	and_gate andgate2(out_1,cin,out_3);
	or_gate orgate1(out_3,out_2,cout);
endmodule

module testbench();
        reg a,b,c;
	wire d,e;
        adder g(a, b, c,d,e);
        initial begin
                $dumpfile("./dump.vcd");
                $dumpvars;
        end
        initial begin
                a = 0;
		b = 0;
		c = 0;
                #1;
                $display("a = %b , b = %b, c = %b => out = %b, cout = %d", a, b, c,d,e);

		a = 0;
                b = 0;
                c = 1;
                #1;
		$display("a = %b , b = %b, c = %b => out = %b, cout = %d", a, b, c,d,e);

		a = 0;
                b = 1;
                c = 0;
                #1;
		$display("a = %b , b = %b, c = %b => out = %b, cout = %d", a, b, c,d,e);


		a = 1;
                b = 0;
                c = 0;
                #1;
		$display("a = %b , b = %b, c = %b => out = %b, cout = %d", a, b, c,d,e);

		a = 1;
                b = 1;
                c = 0;
                #1;
		$display("a = %b , b = %b, c = %b => out = %b, cout = %d", a, b, c,d,e);


		a = 1;
                b = 0;
                c = 1;
                #1;
		$display("a = %b , b = %b, c = %b => out = %b, cout = %d", a, b, c,d,e);

		a = 0;
                b = 1;
                c = 1;
                #1;
		$display("a = %b , b = %b, c = %b => out = %b, cout = %d", a, b, c,d,e);

		a = 1;
                b = 1;
                c = 1;
                #1;
		$display("a = %b , b = %b, c = %b => out = %b, cout = %d", a, b, c,d,e);


        end
endmodule

Simple Binary elements/dump.vcd
$date
	Fri Jul 26 16:32:35 2024
$end
$version
	Icarus Verilog
$end
$timescale
	1s
$end
$scope module half_adder $end
$var wire 1 ! c $end
$var wire 1 " gnd $end
$var wire 1 # in1 $end
$var wire 1 $ in2 $end
$var wire 1 % out $end
$var wire 1 & vdd $end
$scope module andgate $end
$var wire 1 ' gnd $end
$var wire 1 # in1 $end
$var wire 1 $ in2 $end
$var wire 1 ( mos $end
$var wire 1 % out $end
$var wire 1 ) vdd $end
$scope module nand1 $end
$var wire 1 * gnd $end
$var wire 1 # in1 $end
$var wire 1 $ in2 $end
$var wire 1 + nmos_out $end
$var wire 1 ( out $end
$var wire 1 , vdd $end
$upscope $end
$scope module not1 $end
$var wire 1 - gnd $end
$var wire 1 ( in $end
$var wire 1 % out $end
$var wire 1 . vdd $end
$upscope $end
$upscope $end
$scope module xorgate $end
$var wire 1 / gnd $end
$var wire 1 # in1 $end
$var wire 1 $ in2 $end
$var wire 1 ! out $end
$var wire 1 0 out_1 $end
$var wire 1 1 out_2 $end
$var wire 1 2 out_3 $end
$var wire 1 3 vdd $end
$scope module and1 $end
$var wire 1 4 gnd $end
$var wire 1 # in1 $end
$var wire 1 $ in2 $end
$var wire 1 5 mos $end
$var wire 1 1 out $end
$var wire 1 6 vdd $end
$scope module nand1 $end
$var wire 1 7 gnd $end
$var wire 1 # in1 $end
$var wire 1 $ in2 $end
$var wire 1 8 nmos_out $end
$var wire 1 5 out $end
$var wire 1 9 vdd $end
$upscope $end
$scope module not1 $end
$var wire 1 : gnd $end
$var wire 1 5 in $end
$var wire 1 1 out $end
$var wire 1 ; vdd $end
$upscope $end
$upscope $end
$scope module and2 $end
$var wire 1 < gnd $end
$var wire 1 0 in1 $end
$var wire 1 2 in2 $end
$var wire 1 = mos $end
$var wire 1 ! out $end
$var wire 1 > vdd $end
$scope module nand1 $end
$var wire 1 ? gnd $end
$var wire 1 0 in1 $end
$var wire 1 2 in2 $end
$var wire 1 @ nmos_out $end
$var wire 1 = out $end
$var wire 1 A vdd $end
$upscope $end
$scope module not1 $end
$var wire 1 B gnd $end
$var wire 1 = in $end
$var wire 1 ! out $end
$var wire 1 C vdd $end
$upscope $end
$upscope $end
$scope module not1 $end
$var wire 1 D gnd $end
$var wire 1 1 in $end
$var wire 1 2 out $end
$var wire 1 E vdd $end
$upscope $end
$scope module or1 $end
$var wire 1 F gnd $end
$var wire 1 # in1 $end
$var wire 1 $ in2 $end
$var wire 1 G mos $end
$var wire 1 0 out $end
$var wire 1 H vdd $end
$scope module nand1 $end
$var wire 1 I gnd $end
$var wire 1 # in1 $end
$var wire 1 $ in2 $end
$var wire 1 G out $end
$var wire 1 J pmos_out $end
$var wire 1 K vdd $end
$upscope $end
$scope module not1 $end
$var wire 1 L gnd $end
$var wire 1 G in $end
$var wire 1 0 out $end
$var wire 1 M vdd $end
$upscope $end
$upscope $end
$upscope $end
$upscope $end
$scope module testbench $end
$var wire 1 N d $end
$var wire 1 O e $end
$var reg 1 P a $end
$var reg 1 Q b $end
$var reg 1 R c $end
$scope module g $end
$var wire 1 R cin $end
$var wire 1 N cout $end
$var wire 1 S gnd $end
$var wire 1 P in1 $end
$var wire 1 Q in2 $end
$var wire 1 O out $end
$var wire 1 T out_1 $end
$var wire 1 U out_2 $end
$var wire 1 V out_3 $end
$var wire 1 W vdd $end
$scope module andgate1 $end
$var wire 1 X gnd $end
$var wire 1 P in1 $end
$var wire 1 Q in2 $end
$var wire 1 Y mos $end
$var wire 1 U out $end
$var wire 1 Z vdd $end
$scope module nand1 $end
$var wire 1 [ gnd $end
$var wire 1 P in1 $end
$var wire 1 Q in2 $end
$var wire 1 \ nmos_out $end
$var wire 1 Y out $end
$var wire 1 ] vdd $end
$upscope $end
$scope module not1 $end
$var wire 1 ^ gnd $end
$var wire 1 Y in $end
$var wire 1 U out $end
$var wire 1 _ vdd $end
$upscope $end
$upscope $end
$scope module andgate2 $end
$var wire 1 ` gnd $end
$var wire 1 T in1 $end
$var wire 1 R in2 $end
$var wire 1 a mos $end
$var wire 1 V out $end
$var wire 1 b vdd $end
$scope module nand1 $end
$var wire 1 c gnd $end
$var wire 1 T in1 $end
$var wire 1 R in2 $end
$var wire 1 d nmos_out $end
$var wire 1 a out $end
$var wire 1 e vdd $end
$upscope $end
$scope module not1 $end
$var wire 1 f gnd $end
$var wire 1 a in $end
$var wire 1 V out $end
$var wire 1 g vdd $end
$upscope $end
$upscope $end
$scope module orgate1 $end
$var wire 1 h gnd $end
$var wire 1 V in1 $end
$var wire 1 U in2 $end
$var wire 1 i mos $end
$var wire 1 N out $end
$var wire 1 j vdd $end
$scope module nand1 $end
$var wire 1 k gnd $end
$var wire 1 V in1 $end
$var wire 1 U in2 $end
$var wire 1 i out $end
$var wire 1 l pmos_out $end
$var wire 1 m vdd $end
$upscope $end
$scope module not1 $end
$var wire 1 n gnd $end
$var wire 1 i in $end
$var wire 1 N out $end
$var wire 1 o vdd $end
$upscope $end
$upscope $end
$scope module xorgate1 $end
$var wire 1 p gnd $end
$var wire 1 P in1 $end
$var wire 1 Q in2 $end
$var wire 1 T out $end
$var wire 1 q out_1 $end
$var wire 1 r out_2 $end
$var wire 1 s out_3 $end
$var wire 1 t vdd $end
$scope module and1 $end
$var wire 1 u gnd $end
$var wire 1 P in1 $end
$var wire 1 Q in2 $end
$var wire 1 v mos $end
$var wire 1 r out $end
$var wire 1 w vdd $end
$scope module nand1 $end
$var wire 1 x gnd $end
$var wire 1 P in1 $end
$var wire 1 Q in2 $end
$var wire 1 y nmos_out $end
$var wire 1 v out $end
$var wire 1 z vdd $end
$upscope $end
$scope module not1 $end
$var wire 1 { gnd $end
$var wire 1 v in $end
$var wire 1 r out $end
$var wire 1 | vdd $end
$upscope $end
$upscope $end
$scope module and2 $end
$var wire 1 } gnd $end
$var wire 1 q in1 $end
$var wire 1 s in2 $end
$var wire 1 ~ mos $end
$var wire 1 T out $end
$var wire 1 !" vdd $end
$scope module nand1 $end
$var wire 1 "" gnd $end
$var wire 1 q in1 $end
$var wire 1 s in2 $end
$var wire 1 #" nmos_out $end
$var wire 1 ~ out $end
$var wire 1 $" vdd $end
$upscope $end
$scope module not1 $end
$var wire 1 %" gnd $end
$var wire 1 ~ in $end
$var wire 1 T out $end
$var wire 1 &" vdd $end
$upscope $end
$upscope $end
$scope module not1 $end
$var wire 1 '" gnd $end
$var wire 1 r in $end
$var wire 1 s out $end
$var wire 1 (" vdd $end
$upscope $end
$scope module or1 $end
$var wire 1 )" gnd $end
$var wire 1 P in1 $end
$var wire 1 Q in2 $end
$var wire 1 *" mos $end
$var wire 1 q out $end
$var wire 1 +" vdd $end
$scope module nand1 $end
$var wire 1 ," gnd $end
$var wire 1 P in1 $end
$var wire 1 Q in2 $end
$var wire 1 *" out $end
$var wire 1 -" pmos_out $end
$var wire 1 ." vdd $end
$upscope $end
$scope module not1 $end
$var wire 1 /" gnd $end
$var wire 1 *" in $end
$var wire 1 q out $end
$var wire 1 0" vdd $end
$upscope $end
$upscope $end
$upscope $end
$scope module xorgate2 $end
$var wire 1 1" gnd $end
$var wire 1 T in1 $end
$var wire 1 R in2 $end
$var wire 1 O out $end
$var wire 1 2" out_1 $end
$var wire 1 3" out_2 $end
$var wire 1 4" out_3 $end
$var wire 1 5" vdd $end
$scope module and1 $end
$var wire 1 6" gnd $end
$var wire 1 T in1 $end
$var wire 1 R in2 $end
$var wire 1 7" mos $end
$var wire 1 3" out $end
$var wire 1 8" vdd $end
$scope module nand1 $end
$var wire 1 9" gnd $end
$var wire 1 T in1 $end
$var wire 1 R in2 $end
$var wire 1 :" nmos_out $end
$var wire 1 7" out $end
$var wire 1 ;" vdd $end
$upscope $end
$scope module not1 $end
$var wire 1 <" gnd $end
$var wire 1 7" in $end
$var wire 1 3" out $end
$var wire 1 =" vdd $end
$upscope $end
$upscope $end
$scope module and2 $end
$var wire 1 >" gnd $end
$var wire 1 2" in1 $end
$var wire 1 4" in2 $end
$var wire 1 ?" mos $end
$var wire 1 O out $end
$var wire 1 @" vdd $end
$scope module nand1 $end
$var wire 1 A" gnd $end
$var wire 1 2" in1 $end
$var wire 1 4" in2 $end
$var wire 1 B" nmos_out $end
$var wire 1 ?" out $end
$var wire 1 C" vdd $end
$upscope $end
$scope module not1 $end
$var wire 1 D" gnd $end
$var wire 1 ?" in $end
$var wire 1 O out $end
$var wire 1 E" vdd $end
$upscope $end
$upscope $end
$scope module not1 $end
$var wire 1 F" gnd $end
$var wire 1 3" in $end
$var wire 1 4" out $end
$var wire 1 G" vdd $end
$upscope $end
$scope module or1 $end
$var wire 1 H" gnd $end
$var wire 1 T in1 $end
$var wire 1 R in2 $end
$var wire 1 I" mos $end
$var wire 1 2" out $end
$var wire 1 J" vdd $end
$scope module nand1 $end
$var wire 1 K" gnd $end
$var wire 1 T in1 $end
$var wire 1 R in2 $end
$var wire 1 I" out $end
$var wire 1 L" pmos_out $end
$var wire 1 M" vdd $end
$upscope $end
$scope module not1 $end
$var wire 1 N" gnd $end
$var wire 1 I" in $end
$var wire 1 2" out $end
$var wire 1 O" vdd $end
$upscope $end
$upscope $end
$upscope $end
$upscope $end
$upscope $end
$enddefinitions $end
#0
$dumpvars
1O"
0N"
1M"
1L"
0K"
1J"
1I"
0H"
1G"
0F"
1E"
0D"
1C"
0B"
0A"
1@"
1?"
0>"
1="
0<"
1;"
z:"
09"
18"
17"
06"
15"
14"
03"
02"
01"
10"
0/"
1."
1-"
0,"
1+"
1*"
0)"
1("
0'"
1&"
0%"
1$"
0#"
0""
1!"
1~
0}
1|
0{
1z
zy
0x
1w
1v
0u
1t
1s
0r
0q
0p
1o
0n
1m
1l
0k
1j
1i
0h
1g
0f
1e
zd
0c
1b
1a
0`
1_
0^
1]
z\
0[
1Z
1Y
0X
1W
0V
0U
0T
0S
0R
0Q
0P
0O
0N
1M
0L
1K
xJ
0I
1H
xG
0F
1E
0D
1C
0B
1A
x@
0?
1>
x=
0<
1;
0:
19
x8
07
16
x5
04
13
x2
x1
x0
0/
1.
0-
1,
x+
0*
1)
x(
0'
1&
x%
z$
z#
0"
x!
$end
#1
0d
0:"
1O
0?"
12"
0I"
1R
#2
zd
z:"
0R
0\
0y
1l
0N
1i
0V
1a
1O
0?"
0B"
14"
03"
17"
zL"
1T
0~
1q
0*"
1Q
#3
z\
zy
0Q
0N
1i
0U
1Y
zL"
1O
0?"
12"
0I"
1T
0~
0#"
1s
0r
1v
z-"
1P
#4
1N
0i
1U
0Y
0\
1L"
0O
1?"
02"
1I"
0T
1~
z#"
0s
1r
0v
0y
1Q
#5
zl
1V
0a
0d
zB"
04"
13"
07"
0:"
1R
1N
0i
0U
1Y
z\
zL"
0O
1?"
12"
0I"
1T
0~
0#"
1s
0r
1v
zy
0Q
#6
0\
0y
1Q
1-"
zl
1N
0i
1V
0a
0O
1?"
zB"
04"
13"
07"
zL"
1T
0~
1q
0*"
0P
#7
1U
0Y
1l
1N
0i
0V
1a
1O
0?"
0B"
14"
03"
17"
1L"
0T
1~
z#"
0s
1r
0v
z-"
1P
